climate_diagnostics/__init__.py
climate_diagnostics/py.typed
climate_diagnostics/TimeSeries/TimeSeries.py
climate_diagnostics/TimeSeries/Trends.py
climate_diagnostics/TimeSeries/__init__.py
climate_diagnostics/models/__init__.py
climate_diagnostics/models/rce.py
climate_diagnostics/plots/__init__.py
climate_diagnostics/plots/plot.py
climate_diagnostics/utils/__init__.py
climate_diagnostics/utils/coord_utils.py
climate_diagnostics/utils/dask_utils.py
climate_diagnostics/utils/data_utils.py
climate_diagnostics/utils/plot_utils.py
climate_diagnostics-1.3.0.dist-info/licenses/LICENSE
climate_diagnostics-1.3.0.dist-info/METADATA
climate_diagnostics-1.3.0.dist-info/WHEEL
climate_diagnostics-1.3.0.dist-info/top_level.txt
climate_diagnostics-1.3.0.dist-info/RECORD
