Metadata-Version: 2.4
Name: climate_diagnostics
Version: 1.3.0
Summary: Production-ready climate diagnostics tools with advanced chunking optimization for analyzing and visualizing climate data
Author-email: Pranay Chakraborty <pranay.chakraborty.personal@gmail.com>
License-Expression: MIT
Project-URL: Homepage, https://github.com/pranaychakra/climate_diagnostics
Project-URL: Documentation, https://climate-diagnostics.readthedocs.io/
Project-URL: Repository, https://github.com/pranaychakra/climate_diagnostics.git
Project-URL: Bug Tracker, https://github.com/pranaychakra/climate_diagnostics/issues
Project-URL: Changelog, https://github.com/pranaychakra/climate_diagnostics/blob/main/docs/source/changelog.rst
Classifier: Development Status :: 4 - Beta
Classifier: Intended Audience :: Science/Research
Classifier: Programming Language :: Python :: 3
Classifier: Programming Language :: Python :: 3.9
Classifier: Programming Language :: Python :: 3.10
Classifier: Programming Language :: Python :: 3.11
Classifier: Programming Language :: Python :: 3.12
Classifier: Operating System :: OS Independent
Classifier: Topic :: Scientific/Engineering :: Atmospheric Science
Classifier: Topic :: Scientific/Engineering :: Visualization
Classifier: Topic :: Scientific/Engineering
Classifier: Intended Audience :: Developers
Classifier: Natural Language :: English
Requires-Python: >=3.9
License-File: LICENSE
Requires-Dist: xarray>=0.20.0
Requires-Dist: dask[complete]>=2021.11.0
Requires-Dist: netCDF4>=1.5.0
Requires-Dist: bottleneck>=1.3.0
Requires-Dist: matplotlib>=3.5.0
Requires-Dist: numpy>=1.20.0
Requires-Dist: scipy>=1.7.0
Requires-Dist: pandas>=1.3.0
Requires-Dist: statsmodels>=0.13.0
Requires-Dist: cartopy>=0.20.0
Provides-Extra: dev
Requires-Dist: pytest>=6.0; extra == "dev"
Requires-Dist: pytest-mock>=3.0; extra == "dev"
Requires-Dist: pytest-cov>=3.0; extra == "dev"
Requires-Dist: flake8>=4.0; extra == "dev"
Requires-Dist: mypy>=0.900; extra == "dev"
Requires-Dist: black>=22.0; extra == "dev"
Requires-Dist: isort>=5.0; extra == "dev"
Requires-Dist: pre-commit>=2.0; extra == "dev"
Requires-Dist: tox>=3.20; extra == "dev"
Requires-Dist: build>=0.8; extra == "dev"
Requires-Dist: twine>=4.0; extra == "dev"
Requires-Dist: check-manifest>=0.48; extra == "dev"
Provides-Extra: test
Requires-Dist: pytest>=6.0; extra == "test"
Requires-Dist: pytest-mock>=3.0; extra == "test"
Requires-Dist: pytest-cov>=3.0; extra == "test"
Provides-Extra: docs
Requires-Dist: sphinx>=4.0; extra == "docs"
Requires-Dist: furo>=2022.6.21; extra == "docs"
Requires-Dist: sphinx-copybutton>=0.5.0; extra == "docs"
Requires-Dist: sphinx-design>=0.3.0; extra == "docs"
Requires-Dist: myst-parser>=0.18.0; extra == "docs"
Requires-Dist: jupyter>=1.0; extra == "docs"
Requires-Dist: ipykernel>=6.0; extra == "docs"
Provides-Extra: all
Requires-Dist: climate_diagnostics[dev,docs,test]; extra == "all"
Dynamic: license-file
